pyastrx/__init__.py
pyastrx/config.py
pyastrx/data_typing.py
pyastrx/exceptions.py
pyastrx/folder_utils.py
pyastrx/axml/__init__.py
pyastrx/axml/python/__init__.py
pyastrx/axml/python/ast2xml.py
pyastrx/axml/python/things2ast.py
pyastrx/axml/yaml/__init__.py
pyastrx/axml/yaml/composer.py
pyastrx/axml/yaml/loader.py
pyastrx/axml/yaml/nodes.py
pyastrx/axml/yaml/yaml2xml.py
pyastrx/frontend/__init__.py
pyastrx/frontend/cli.py
pyastrx/frontend/manager.py
pyastrx/frontend/mypyq.py
pyastrx/frontend/state_machine.py
pyastrx/inference/__init__.py
pyastrx/inference/mypy.py
pyastrx/inference/mypy_visitor.py
pyastrx/inference/normalization.py
pyastrx/inference/pyre.py
pyastrx/report/__init__.py
pyastrx/report/humanize.py
pyastrx/report/stdout.py
pyastrx/search/__init__.py
pyastrx/search/cache.py
pyastrx/search/main.py
pyastrx/search/txt_tools.py
pyastrx/search/xml_search.py
pyastrx/xml/__init__.py
pyastrx/xml/misc.py
pyastrx/xml/xpath_expressions.py
pyastrx/xml/xpath_extensions.py
pyastrx-0.6.1.dist-info/AUTHORS.md
pyastrx-0.6.1.dist-info/LICENSE.md
pyastrx-0.6.1.dist-info/METADATA
pyastrx-0.6.1.dist-info/WHEEL
pyastrx-0.6.1.dist-info/entry_points.txt
pyastrx-0.6.1.dist-info/top_level.txt
pyastrx-0.6.1.dist-info/RECORD
