Metadata-Version: 2.1
Name: pyastrx
Version: 0.6.1
Summary: 'Simple projects are all alike; each complexproject is complex in its own way.' - (adapted from Tolstoy's Anna Karenina)
Home-page: https://github.com/pyastrx/pyastrx
Author: Bruno Messias
Author-email: devmessias@gmail.com
License: MIT
Keywords: ast,xpath,yaml,linter,parser,refactoring tool,vscode,pyre,pyre-linter
Classifier: Development Status :: 3 - Alpha
Classifier: Programming Language :: Python
Classifier: Intended Audience :: Developers
Classifier: Operating System :: OS Independent
Classifier: License :: OSI Approved :: MIT License
Classifier: Natural Language :: English
License-File: LICENSE.md
License-File: AUTHORS.md
Requires-Dist: colorama==0.4.6
Requires-Dist: gast==0.6.0
Requires-Dist: lxml==5.3.0
Requires-Dist: prompt-toolkit==3.0.47
Requires-Dist: pygments
Requires-Dist: pyyaml==6.0.2
Requires-Dist: rich
Requires-Dist: typing-extensions==4.12.2
Requires-Dist: watchdog
Requires-Dist: wcwidth==0.2.13
